{"[0,2,2,2,2,2,2]":"WholeTone","[0,2,2,1,2,2,2]":"Major AKA Ionian","[0,2,2,2,2,1,2]":"Major7s4s5","[0,2,1,2,2,2,1]":"Dorian","[0,1,2,2,2,1,2]":"Phrygian AKA Istrian","[0,2,2,2,1,2,2]":"Lydian","[0,2,2,2,1,2,1]":"LydianDominant AKA Acoustic","[0,2,2,1,2,2,1]":"Mixolydian AKA MelodicMinorDescending","[0,2,2,1,2,1,2]":"MixolydianFlat6 AKA Hindu","[0,1,2,2,1,2,2]":"Locrian","[0,1,2,1,2,2,2]":"SuperLocrian AKA Spanish","[0,2,1,2,2,1,2]":"Minor AKA Aeolian","[0,1,2,2,2,2,1]":"Minor7b9","[0,2,1,2,1,2,2]":"Minor7b5 AKA HalfDiminished","[0,2,2,1,2,1,3]":"HarmonicMajor","[0,2,1,2,2,1,3]":"HarmonicMinor","[0,1,3,1,2,1,3]":"DoubleHarmonic AKA HungarianGypsy AKA Byzantine","[0,2,1,2,2,2,2]":"MelodicMinorAscending","[0,2,2,3,2]":"MajorPentatonic AKA Mongolian","[0,2,1,1,3,2]":"MajorPentatonicBlues","[0,3,2,2,3]":"MinorPentatonic AKA Yo","[0,3,2,1,1,3]":"MinorPentatonicBlues","[0,3,2,1,4,2]":"B5Pentatonic","[0,3,2,2,2,3]":"Minor6Pentatonic","[0,1,3,2,2,2,1]":"EnigmaticMajor","[0,1,2,3,1,3,1]":"EnigmaticMinor","[0,2,1,2,1,2,1,2]":"Dim8Tone","[0,1,2,1,2,1,2,1]":"Dom8Tone","[0,1,2,2,2,2,2]":"NeapolitanMajor","[0,1,2,2,2,1,3]":"NeapolitanMinor","[0,3,1,2,1,2,1]":"HungarianMajor","[0,2,1,3,1,1,3]":"HungarianMinor","[0,1,2,1,1,1,2,2]":"Spanish8Tone AKA Jewish","[0,1,3,1,2,1,2]":"SpanishGypsy AKA Ahavaraba","[0,3,1,3,1,3,1]":"Augmented","[0,2,3,2,2,1,2]":"DominantSuspended","[0,2,2,1,2,1,1,2]":"BebopMajor","[0,2,2,1,2,2,1,1]":"BebopDominant","[0,2,2,2,3,2]":"Mystic","[0,2,2,2,1,1,2]":"Overtone","[0,2,2,2,2,2,1]":"LeadingTone","[0,2,1,4,1]":"Hirojoshi","[0,1,4,1,3]":"JapaneseA","[0,2,3,1,3]":"JapaneseB","[0,1,3,1,1,3,1]":"Oriental","[0,1,4,1,2,3]":"Persian","[0,2,2,1,1,2,2]":"Arabian","[0,1,2,4,1]":"Balinese","[0,2,1,4,2,2]":"Kumoi","[0,1,2,3,1,1]":"Pelog","[0,2,1,2,1,1,1,3]":"Algerian","[0,4,2,1,4]":"Chinese","[0,2,3,2,3]":"Egyptian","[0,2,1,3,1,2,1]":"Romainian AKA UkranianDorian","[0,1,4,2,3]":"Insen","[0,1,4,1,4]":"Iwato","[0,2,3,2,2]":"Scottish","[0,1,3,2,1,3]":"Petrushka"}